MultiRelay/__init__.py
MultiRelay-0.0.1.dist-info/METADATA
MultiRelay-0.0.1.dist-info/RECORD
MultiRelay-0.0.1.dist-info/WHEEL
MultiRelay-0.0.1.dist-info/top_level.txt
